szabolcs/__init__.py
szabolcs-0.1.1.dist-info/METADATA
szabolcs-0.1.1.dist-info/WHEEL
szabolcs-0.1.1.dist-info/top_level.txt
szabolcs-0.1.1.dist-info/RECORD
